pjbank/__init__.py
pjbank/api.py
pjbank/config.py
pjbank/contadigital/__init__.py
pjbank/contadigital/consultas.py
pjbank/contadigital/credenciamento.py
pjbank/contadigital/subcontas.py
pjbank/contadigital/transacoes.py
pjbank/recebimentos/__init__.py
pjbank/recebimentos/boleto.py
pjbank/recebimentos/cartaocredito.py
pjbank-0.9.dev4.dist-info/DESCRIPTION.rst
pjbank-0.9.dev4.dist-info/METADATA
pjbank-0.9.dev4.dist-info/RECORD
pjbank-0.9.dev4.dist-info/WHEEL
pjbank-0.9.dev4.dist-info/metadata.json
pjbank-0.9.dev4.dist-info/top_level.txt
