Metadata-Version: 2.0
Name: pjbank
Version: 0.9.dev4
Summary: PJBank Python SDK
Home-page: https://github.com/pjbank/pjbank-python-sdk
Author: Raphael Mattos
Author-email: raphael.mattos@pjbank.com.br
License: MIT
Download-URL: https://github.com/pjbank/pjbank-python-sdk/archive/0.9dev4.tar.gz
Keywords: pjbank contadigital boleto cartao pagamentos recebimentos
Platform: UNKNOWN
Classifier: Development Status :: 4 - Beta
Classifier: Intended Audience :: Developers
Classifier: Topic :: Software Development :: Build Tools
Classifier: License :: OSI Approved :: MIT License
Classifier: Programming Language :: Python :: 2
Classifier: Programming Language :: Python :: 2.7
Classifier: Programming Language :: Python :: 3
Classifier: Programming Language :: Python :: 3.3
Classifier: Programming Language :: Python :: 3.4
Classifier: Programming Language :: Python :: 3.5
Classifier: Programming Language :: Python :: 3.6
Requires-Dist: requests
Provides-Extra: dev
Requires-Dist: check-manifest; extra == 'dev'
Provides-Extra: test
Requires-Dist: coverage; extra == 'test'
